setup.py
pivotalpy/__init__.py
pivotalpy/client.py
pivotalpy/project.py
pivotalpy/story.py
pivotalpy.egg-info/PKG-INFO
pivotalpy.egg-info/SOURCES.txt
pivotalpy.egg-info/dependency_links.txt
pivotalpy.egg-info/requires.txt
pivotalpy.egg-info/top_level.txt
tests/__init__.py
tests/test_projects.py
tests/test_stories.py