Metadata-Version: 1.0
Name: pivotalpy
Version: 0.1
Summary: Wrapper for Pivotal Tracker API v5
Home-page: UNKNOWN
Author: UNKNOWN
Author-email: UNKNOWN
License: UNKNOWN
Platform: UNKNOWN
